pyosf/__init__.py
pyosf/constants.py
pyosf/exceptions.py
pyosf/local.py
pyosf/project.py
pyosf/remote.py
pyosf/sync.py
pyosf/tools.py
pyosf-1.0.5.dist-info/DESCRIPTION.rst
pyosf-1.0.5.dist-info/METADATA
pyosf-1.0.5.dist-info/RECORD
pyosf-1.0.5.dist-info/WHEEL
pyosf-1.0.5.dist-info/metadata.json
pyosf-1.0.5.dist-info/pbr.json
pyosf-1.0.5.dist-info/top_level.txt
