Metadata-Version: 1.1
Name: pyosf
Version: 1.0.5
Summary: Python lib for synching with OpenScienceFramework projects
Home-page: https://github.com/psychopy/pyosf
Author: Jon Peirce
Author-email: jon.peirce@gmail.com
License: MIT
Keywords: Open Science Framework PsychoPy
Platform: UNKNOWN
Classifier: Development Status :: 3 - Alpha
Classifier: Intended Audience :: Developers
Classifier: License :: OSI Approved :: MIT License
Classifier: Programming Language :: Python :: 2
Classifier: Programming Language :: Python :: 2.7
Classifier: Programming Language :: Python :: 3
Classifier: Programming Language :: Python :: 3.3
Classifier: Programming Language :: Python :: 3.4
Classifier: Programming Language :: Python :: 3.5
Classifier: Operating System :: MacOS :: MacOS X
Classifier: Operating System :: Microsoft :: Windows
Classifier: Operating System :: POSIX
